sjgeofire/__init__.py
sjgeofire/jclass/__init__.py
sjgeofire/jclass/geofire.py
sjgeofire/jclass/geofireutils.py
sjgeofire/jclass/geolocation.py
sjgeofire/jclass/geoutils.py
sjgeofire/jinterface/__init__.py
sjgeofire/jinterface/completion.py
sjgeofire/jinterface/geoquery.py
sjgeofire/jinterface/geoquerydata.py
sjgeofire/jinterface/locationcallback.py
sjgeofire/tools/__init__.py
sjgeofire/tools/mixin.py
sjgeofire/tools/serialize.py
sjgeofire-0.3.0.dist-info/METADATA
sjgeofire-0.3.0.dist-info/WHEEL
sjgeofire-0.3.0.dist-info/RECORD
